src/__init__.py
src/main.py
src/core/__init__.py
src/core/command_processor.py
src/git/__init__.py
src/git/repo.py
src/git/submodule.py
src/model/__init__.py
src/model/service.py
src/task/__init__.py
src/task/task_handler.py
git_compose-0.0.2.dist-info/LICENSE
git_compose-0.0.2.dist-info/METADATA
git_compose-0.0.2.dist-info/WHEEL
git_compose-0.0.2.dist-info/entry_points.txt
git_compose-0.0.2.dist-info/top_level.txt
git_compose-0.0.2.dist-info/RECORD
